CHANGELOG.txt
LICENSE.txt
MANIFEST.in
README.md
setup.py
iewil.egg-info/SOURCES.txt
iewil.egg-info/dependency_links.txt
iewil.egg-info/top_level.txt
modulku/__init__.py
modulku.egg-info/PKG-INFO
modulku.egg-info/SOURCES.txt
modulku.egg-info/dependency_links.txt
modulku.egg-info/top_level.txt