Metadata-Version: 2.1
Name: modulku
Version: 0.0.1
Summary: Modul pribadi
Home-page: https://github.com/iewilmaestro/modulku_python
Author: iewil
Author-email: purna.iera@gmail.com
License: MIT
Keywords: python php
Classifier: Development Status :: 1 - Planning
Classifier: Intended Audience :: Education
Classifier: Operating System :: OS Independent
Classifier: License :: OSI Approved :: MIT License
Classifier: Programming Language :: Python
License-File: LICENSE.txt
